Metadata-Version: 2.1
Name: spd-stats
Version: 0.1.0
Summary: Statistical Probability Distributions Package
Home-page: UNKNOWN
Author: Pradeep Sahani
Author-email: sahanipradeep5529@gmail.com
License: UNKNOWN
Platform: UNKNOWN
Requires-Python: >=3.6
